langgraph_bigtool-0.0.3.dist-info/METADATA
langgraph_bigtool-0.0.3.dist-info/WHEEL
langgraph_bigtool-0.0.3.dist-info/entry_points.txt
langgraph_bigtool-0.0.3.dist-info/licenses/LICENSE
langgraph_bigtool/__init__.py
langgraph_bigtool/graph.py
langgraph_bigtool/tools.py
langgraph_bigtool/utils.py
langgraph_bigtool-0.0.3.dist-info/RECORD
