Metadata-Version: 2.1
Name: langgraph-bigtool
Version: 0.0.3
Summary: Build LangGraph agents with large numbers of tools
Requires-Python: >=3.10
Requires-Dist: langgraph>=0.3.0
